{
    "name": "Floodplain & River water surface elevations",
    "dates": "2012 - 2016",
    "contact": "Drew Nichols",
    "details": "Logger data showing elevations of water surfaces for river, breach, and floodplain locations. Loggers collected data at a regular 15 minute intervals. Temperature was also collected at some locations. See metadata spreadsheet for locations and time period of the various monitoring locations.",
    "downloads": [{
        "name": "Depth_WSE_WY2012.xlsx", "url": "/data/floodplain-river-levels/Depth_WSE_WY2012.xlsx"},{
            "name": "Depth_WSE_WY2013.xlsx", "url": "/data/floodplain-river-levels/Depth_WSE_WY2013.xlsx"},{
                "name": "Depth_WSE_WY2014.xlsx", "url": "/data/floodplain-river-levels/Depth_WSE_WY2014.xlsx"},
                {"name": "Depth_WSE_WY2015.xlsx", "url": "/data/floodplain-river-levels/Depth_WSE_WY2015.xlsx"},
            {"name": "Depth_WSE_WY2016.xlsx", "url": "/data/floodplain-river-levels/Depth_WSE_WY2016.xlsx"},
        {"name": "Floodplain-river-levels-logger-metadata.csv", "url": "/data/floodplain-river-levels/floodplain-river-levels-logger-metadata.csv"}],
    "variables": ["Water Surface Elevation", "Temperature"],

    "tabs": {
            "table": true,
            "map": true,
            "download": true,
            "customMap": false
        },
    "table": {
            "url": "/data/floodplain-river-levels/floodplain-river-levels-logger-metadata.json",
            "columns": ["Location", "Type", "Elevation", "2012", "2013", "2014", "2015", "2016"]
        }
}
